LICENSE
MANIFEST.in
README.md
requirements.txt
setup.cfg
setup.py
django_mp_gallery.egg-info/PKG-INFO
django_mp_gallery.egg-info/SOURCES.txt
django_mp_gallery.egg-info/dependency_links.txt
django_mp_gallery.egg-info/requires.txt
django_mp_gallery.egg-info/top_level.txt
gallery/__init__.py
gallery/photos/__init__.py
gallery/photos/admin.py
gallery/photos/models.py
gallery/photos/translation.py
gallery/photos/urls.py
gallery/photos/views.py
gallery/photos/locale/en/LC_MESSAGES/django.mo
gallery/photos/locale/en/LC_MESSAGES/django.po
gallery/photos/locale/uk/LC_MESSAGES/django.mo
gallery/photos/locale/uk/LC_MESSAGES/django.po
gallery/photos/migrations/0001_initial.py
gallery/photos/migrations/0002_auto_20170224_0918.py
gallery/photos/migrations/0003_auto_20170329_0816.py
gallery/photos/migrations/0004_auto_20171103_1246.py
gallery/photos/migrations/__init__.py
gallery/videos/__init__.py
gallery/videos/admin.py
gallery/videos/models.py
gallery/videos/translation.py
gallery/videos/urls.py
gallery/videos/views.py
gallery/videos/locale/en/LC_MESSAGES/django.mo
gallery/videos/locale/en/LC_MESSAGES/django.po
gallery/videos/locale/uk/LC_MESSAGES/django.mo
gallery/videos/locale/uk/LC_MESSAGES/django.po
gallery/videos/migrations/0001_initial.py
gallery/videos/migrations/0002_auto_20170329_0817.py
gallery/videos/migrations/0003_auto_20171103_1248.py
gallery/videos/migrations/__init__.py