Metadata-Version: 1.1
Name: django-mp-gallery
Version: 3.0
Summary: Django gallery app
Home-page: https://github.com/pmaigutyak/mp-gallery
Author: Paul Maigutyak
Author-email: pmaigutyak@gmail.com
License: MIT
Download-URL: https://github.com/pmaigutyak/mp-gallery/archive/3.0.tar.gz
Platform: UNKNOWN
